{
  "id" : {
    "entityId" : "EN_DISBURSOP_905",
    "version" : "1.0.0"
  },
  "description" : null,
  "name" : "DisbursementReports",
  "tableName" : null,
  "_transient" : null,
  "databaseName" : null,
  "dbmsName" : null,
  "customizationLayer" : 0,
  "customizationLayerDescription" : "ECU",
  "attributes" : [ {
    "attributeId" : "AT28_CODETLDV905",
    "columnName" : null,
    "falseValue" : null,
    "pkStr" : "F",
    "length" : 0,
    "name" : "code",
    "order" : 1,
    "requiredStr" : "F",
    "transientStr" : "F",
    "trueValue" : null,
    "dataType" : "String",
    "objectType" : null,
    "autoGeneratedStr" : "F",
    "expression" : null,
    "customizationLayer" : 0,
    "customizationLayerDescription" : "ECU",
    "listValues" : null,
    "labelId" : null,
    "entityPk" : {
      "entityId" : "EN_DISBURSOP_905",
      "version" : "1.0.0"
    },
    "label" : null,
    "transient" : false,
    "required" : false,
    "pk" : false,
    "autoGenerated" : false
  }, {
    "attributeId" : "AT28_CONSOLDD905",
    "columnName" : null,
    "falseValue" : null,
    "pkStr" : "F",
    "length" : 0,
    "name" : "consolidatedAccount",
    "order" : 4,
    "requiredStr" : "F",
    "transientStr" : "F",
    "trueValue" : null,
    "dataType" : "Boolean",
    "objectType" : null,
    "autoGeneratedStr" : "F",
    "expression" : null,
    "customizationLayer" : 0,
    "customizationLayerDescription" : "ECU",
    "listValues" : null,
    "labelId" : null,
    "entityPk" : {
      "entityId" : "EN_DISBURSOP_905",
      "version" : "1.0.0"
    },
    "label" : null,
    "transient" : false,
    "required" : false,
    "pk" : false,
    "autoGenerated" : false
  }, {
    "attributeId" : "AT29_GROUPSTT905",
    "columnName" : null,
    "falseValue" : null,
    "pkStr" : "F",
    "length" : 0,
    "name" : "groupStatement",
    "order" : 3,
    "requiredStr" : "F",
    "transientStr" : "F",
    "trueValue" : null,
    "dataType" : "Boolean",
    "objectType" : null,
    "autoGeneratedStr" : "F",
    "expression" : null,
    "customizationLayer" : 0,
    "customizationLayerDescription" : "ECU",
    "listValues" : null,
    "labelId" : null,
    "entityPk" : {
      "entityId" : "EN_DISBURSOP_905",
      "version" : "1.0.0"
    },
    "label" : null,
    "transient" : false,
    "required" : false,
    "pk" : false,
    "autoGenerated" : false
  }, {
    "attributeId" : "AT66_GROUPAZL905",
    "columnName" : null,
    "falseValue" : null,
    "pkStr" : "F",
    "length" : 0,
    "name" : "groupAmortizationTable",
    "order" : 6,
    "requiredStr" : "F",
    "transientStr" : "F",
    "trueValue" : null,
    "dataType" : "Boolean",
    "objectType" : null,
    "autoGeneratedStr" : "F",
    "expression" : null,
    "customizationLayer" : 0,
    "customizationLayerDescription" : "ECU",
    "listValues" : null,
    "labelId" : null,
    "entityPk" : {
      "entityId" : "EN_DISBURSOP_905",
      "version" : "1.0.0"
    },
    "label" : null,
    "transient" : false,
    "required" : false,
    "pk" : false,
    "autoGenerated" : false
  }, {
    "attributeId" : "AT77_DISBURTO905",
    "columnName" : null,
    "falseValue" : null,
    "pkStr" : "F",
    "length" : 0,
    "name" : "disbursementOrder",
    "order" : 5,
    "requiredStr" : "F",
    "transientStr" : "F",
    "trueValue" : null,
    "dataType" : "Boolean",
    "objectType" : null,
    "autoGeneratedStr" : "F",
    "expression" : null,
    "customizationLayer" : 0,
    "customizationLayerDescription" : "ECU",
    "listValues" : null,
    "labelId" : null,
    "entityPk" : {
      "entityId" : "EN_DISBURSOP_905",
      "version" : "1.0.0"
    },
    "label" : null,
    "transient" : false,
    "required" : false,
    "pk" : false,
    "autoGenerated" : false
  }, {
    "attributeId" : "AT85_SETTLETE905",
    "columnName" : null,
    "falseValue" : null,
    "pkStr" : "F",
    "length" : 0,
    "name" : "settlementSheet",
    "order" : 2,
    "requiredStr" : "F",
    "transientStr" : "F",
    "trueValue" : null,
    "dataType" : "Boolean",
    "objectType" : null,
    "autoGeneratedStr" : "F",
    "expression" : null,
    "customizationLayer" : 0,
    "customizationLayerDescription" : "ECU",
    "listValues" : null,
    "labelId" : null,
    "entityPk" : {
      "entityId" : "EN_DISBURSOP_905",
      "version" : "1.0.0"
    },
    "label" : null,
    "transient" : false,
    "required" : false,
    "pk" : false,
    "autoGenerated" : false
  } ],
  "transient" : false
}