{
  "id" : {
    "entityId" : "EN_1OMXLHKZV_316",
    "version" : "1.0.0"
  },
  "description" : null,
  "name" : "Entity1",
  "tableName" : null,
  "_transient" : null,
  "databaseName" : null,
  "dbmsName" : null,
  "customizationLayer" : 0,
  "customizationLayerDescription" : "ECU",
  "attributes" : [ {
    "attributeId" : "AT02_1FNWRPMG316",
    "columnName" : null,
    "falseValue" : null,
    "pkStr" : "F",
    "length" : 0,
    "name" : "attribute1",
    "order" : 1,
    "requiredStr" : "F",
    "transientStr" : "F",
    "trueValue" : null,
    "dataType" : "String",
    "objectType" : null,
    "autoGeneratedStr" : "F",
    "expression" : null,
    "customizationLayer" : 0,
    "customizationLayerDescription" : "ECU",
    "listValues" : null,
    "labelId" : null,
    "entityPk" : null,
    "label" : null,
    "transient" : false,
    "pk" : false,
    "autoGenerated" : false,
    "required" : false
  }, {
    "attributeId" : "AT03_2XBYIMTE316",
    "columnName" : null,
    "falseValue" : null,
    "pkStr" : "F",
    "length" : 0,
    "name" : "attribute2",
    "order" : 2,
    "requiredStr" : "F",
    "transientStr" : "F",
    "trueValue" : null,
    "dataType" : "String",
    "objectType" : null,
    "autoGeneratedStr" : "F",
    "expression" : null,
    "customizationLayer" : 0,
    "customizationLayerDescription" : "ECU",
    "listValues" : null,
    "labelId" : null,
    "entityPk" : null,
    "label" : null,
    "transient" : false,
    "pk" : false,
    "autoGenerated" : false,
    "required" : false
  } ],
  "transient" : false
}