<?xml version="1.0" encoding="utf-8"?>
<procedure>
  <database>cob_cartera</database>
  <name>sp_qr_amortiza_web</name>
  <type>SYBASE</type>
  <version>1</version>
  <parameters>
    <parameter name="@i_banco" dataType="varchar" direction="in" />
  </parameters>
  <queries>
    <query>
      <columns>
        <column name="descripcion" />
      </columns>
      <queryText></queryText>
    </query>
    <query>
      <columns>
        <column name="qat_dividendo" />
        <column name="qat_fecha_ven" />
        <column name="qat_saldo_cap" />
        <column name="qat_rubro1" />
        <column name="qat_rubro2" />
        <column name="qat_rubro3" />
        <column name="qat_rubro4" />
        <column name="qat_rubro5" />
        <column name="qat_rubro6" />
        <column name="qat_rubro7" />
        <column name="qat_rubro8" />
        <column name="qat_rubro9" />
        <column name="qat_rubro10" />
        <column name="qat_rubro11" />
        <column name="qat_rubro12" />
        <column name="qat_rubro13" />
        <column name="qat_cuota" />
      </columns>
      <queryText></queryText>
    </query>
  </queries>
</procedure>