{
    "id": {
        "entityId": "EN_LOANWARRY_642",
        "version": "1.0.0"
    },
    "description": null,
    "name": {
        "$ref": "../../ASSTS/relations/componentKeys.json#/Entities/EN_LOANWARRY_642/name"
    },
    "tableName": null,
    "_transient": null,
    "isAutomatic": false,
    "databaseName": null,
    "dbmsName": null,
    "customizationLayer": 0,
    "customizationLayerDescription": "ECU",
    "transient": null,
    "enableAutoCRUD": null,
    "attributes": {
        "AT17_WARRANTY642": {
            "attributeId": "AT17_WARRANTY642",
            "order": 1,
            "name": "warranty",
            "columnName": null,
            "dataType": "String",
            "length": 0,
            "customizationLayer": 0,
            "customizationLayerDescription": "ECU",
            "expression": null,
            "falseValue": null,
            "trueValue": null,
            "listValues": null,
            "objectType": null,
            "pkStr": "F",
            "transientStr": "F",
            "requiredStr": "F",
            "autoGeneratedStr": "F",
            "entityPk": {
                "entityId": "EN_LOANWARRY_642",
                "version": "1.0.0"
            },
            "labelId": null
        },
        "AT77_STATUSAR642": {
            "attributeId": "AT77_STATUSAR642",
            "order": 2,
            "name": "statusWarranty",
            "columnName": null,
            "dataType": "String",
            "length": 0,
            "customizationLayer": 0,
            "customizationLayerDescription": "ECU",
            "expression": null,
            "falseValue": null,
            "trueValue": null,
            "listValues": null,
            "objectType": null,
            "pkStr": "F",
            "transientStr": "F",
            "requiredStr": "F",
            "autoGeneratedStr": "F",
            "entityPk": {
                "entityId": "EN_LOANWARRY_642",
                "version": "1.0.0"
            },
            "labelId": null
        },
        "AT51_DESCRION642": {
            "attributeId": "AT51_DESCRION642",
            "order": 3,
            "name": "description",
            "columnName": null,
            "dataType": "String",
            "length": 0,
            "customizationLayer": 0,
            "customizationLayerDescription": "ECU",
            "expression": null,
            "falseValue": null,
            "trueValue": null,
            "listValues": null,
            "objectType": null,
            "pkStr": "F",
            "transientStr": "F",
            "requiredStr": "F",
            "autoGeneratedStr": "F",
            "entityPk": {
                "entityId": "EN_LOANWARRY_642",
                "version": "1.0.0"
            },
            "labelId": null
        },
        "AT13_CODCLINN642": {
            "attributeId": "AT13_CODCLINN642",
            "order": 4,
            "name": "customerID",
            "columnName": null,
            "dataType": "Integer",
            "length": 0,
            "customizationLayer": 0,
            "customizationLayerDescription": "ECU",
            "expression": null,
            "falseValue": null,
            "trueValue": null,
            "listValues": null,
            "objectType": null,
            "pkStr": "F",
            "transientStr": "F",
            "requiredStr": "F",
            "autoGeneratedStr": "F",
            "entityPk": {
                "entityId": "EN_LOANWARRY_642",
                "version": "1.0.0"
            },
            "labelId": null
        },
        "AT79_CUSTOMER642": {
            "attributeId": "AT79_CUSTOMER642",
            "order": 5,
            "name": "customer",
            "columnName": null,
            "dataType": "String",
            "length": 0,
            "customizationLayer": 0,
            "customizationLayerDescription": "ECU",
            "expression": null,
            "falseValue": null,
            "trueValue": null,
            "listValues": null,
            "objectType": null,
            "pkStr": "F",
            "transientStr": "F",
            "requiredStr": "F",
            "autoGeneratedStr": "F",
            "entityPk": {
                "entityId": "EN_LOANWARRY_642",
                "version": "1.0.0"
            },
            "labelId": null
        },
        "AT25_CURRENAL642": {
            "attributeId": "AT25_CURRENAL642",
            "order": 6,
            "name": "currentValue",
            "columnName": null,
            "dataType": "Currency",
            "length": 0,
            "customizationLayer": 0,
            "customizationLayerDescription": "ECU",
            "expression": null,
            "falseValue": null,
            "trueValue": null,
            "listValues": null,
            "objectType": null,
            "pkStr": "F",
            "transientStr": "F",
            "requiredStr": "F",
            "autoGeneratedStr": "F",
            "entityPk": {
                "entityId": "EN_LOANWARRY_642",
                "version": "1.0.0"
            },
            "labelId": null
        },
        "AT13_CURRENYY642": {
            "attributeId": "AT13_CURRENYY642",
            "order": 7,
            "name": "currencyID",
            "columnName": null,
            "dataType": "Integer",
            "length": 0,
            "customizationLayer": 0,
            "customizationLayerDescription": "ECU",
            "expression": null,
            "falseValue": null,
            "trueValue": null,
            "listValues": null,
            "objectType": null,
            "pkStr": "F",
            "transientStr": "F",
            "requiredStr": "F",
            "autoGeneratedStr": "F",
            "entityPk": {
                "entityId": "EN_LOANWARRY_642",
                "version": "1.0.0"
            },
            "labelId": null
        },
        "AT92_CREATENO642": {
            "attributeId": "AT92_CREATENO642",
            "order": 8,
            "name": "createdOn",
            "columnName": null,
            "dataType": "String",
            "length": 0,
            "customizationLayer": 0,
            "customizationLayerDescription": "ECU",
            "expression": null,
            "falseValue": null,
            "trueValue": null,
            "listValues": null,
            "objectType": null,
            "pkStr": "F",
            "transientStr": "F",
            "requiredStr": "F",
            "autoGeneratedStr": "F",
            "entityPk": {
                "entityId": "EN_LOANWARRY_642",
                "version": "1.0.0"
            },
            "labelId": null
        }
    },
    "moduleId": "ASSTS",
    "isImported": false
}